general_tools/ReParse.py
general_tools/__init__.py
general_tools/cache_func.py
general_tools/config.py
general_tools/config_log.py
general_tools/cut_word.py
general_tools/db_op.py
general_tools/django.py
general_tools/elasticsearch_op.py
general_tools/email.py
general_tools/encrypt.py
general_tools/es.py
general_tools/etl_time.py
general_tools/hive_op.py
general_tools/log.py
general_tools/mongo_op.py
general_tools/mq_api.py
general_tools/mq_decode.py
general_tools/multi_process.py
general_tools/multi_process_thread.py
general_tools/multi_thread_auto.py
general_tools/mysql.py
general_tools/mysql_op.py
general_tools/neo4j_op.py
general_tools/object_id.py
general_tools/plt_graph.py
general_tools/queue.py
general_tools/queue0.py
general_tools/queue2.py
general_tools/redis.py
general_tools/redis_operate.py
general_tools/run_on_time.py
general_tools/spider_op.py
general_tools/sqlalchemy.py
general_tools/sqlserver_op.py
general_tools/url_uuid.py
general_tools/utils.py
general_tools/wechat.py
general_tools-0.5.8.dist-info/METADATA
general_tools-0.5.8.dist-info/WHEEL
general_tools-0.5.8.dist-info/top_level.txt
general_tools-0.5.8.dist-info/RECORD
