Metadata-Version: 2.1
Name: general-tools
Version: 0.5.8
Summary: general tools
Home-page: UNKNOWN
Author: xw0102
Author-email: 15200813194@163.com
License: BSD License
Platform: UNKNOWN
Classifier: Environment :: Web Environment
Classifier: Framework :: Django
Classifier: Framework :: Django :: 2.1
Classifier: Intended Audience :: Developers
Classifier: License :: OSI Approved :: BSD License
Classifier: Operating System :: OS Independent
Classifier: Programming Language :: Python
Classifier: Programming Language :: Python :: 3.5
Classifier: Programming Language :: Python :: 3.6
Classifier: Topic :: Internet :: WWW/HTTP
Classifier: Topic :: Internet :: WWW/HTTP :: Dynamic Content
Requires-Dist: pymongo (>=3.10.1)
Requires-Dist: elasticsearch (>=6.8.1)
Requires-Dist: elasticsearch-dsl (>=6.3.1)
Requires-Dist: python-decouple (>=3.1)
Requires-Dist: redis (>=3.3.11)
Requires-Dist: pycrypto (>=2.6.1)
Requires-Dist: pika (>=0.12)
Requires-Dist: python-dateutil (>=2.7)
Requires-Dist: sqlalchemy (>=1.2)
Requires-Dist: py2neo (>=4.3.0numpy>=1.16.4)
Requires-Dist: pandas (>=1.0.1)
Requires-Dist: pypinyin (>=0.37.0)
Requires-Dist: requests (>=2.22.0)
Requires-Dist: pika (>=0.12.0)
Requires-Dist: PyMySQL (>=0.9.3)
Requires-Dist: selenium (>=3.141.0)
Requires-Dist: shortuuid (>=0.5.0)
Requires-Dist: PyHive (>=0.6.2)
Requires-Dist: threadpool (>=1.3.2)
Requires-Dist: beautifulsoup4 (>=4.9.1)
Requires-Dist: pycryptodome (>=3.9.8)
Requires-Dist: python-dateutil (>=2.8.1)
